gitronics/__init__.py
gitronics/compose_model.py
gitronics/file_discovery.py
gitronics/file_readers.py
gitronics/generate_model.py
gitronics/helpers.py
gitronics/project_checker.py
gitronics/project_manager.py
gitronics-0.3.2.dist-info/METADATA
gitronics-0.3.2.dist-info/WHEEL
gitronics-0.3.2.dist-info/licenses/LICENSE
gitronics-0.3.2.dist-info/RECORD
