Metadata-Version: 2.4
Name: gitronics
Version: 0.3.2
Summary: Automatically build an MCNP from a set of files.
Author-email: Alvaro Cubi <cubiric@hotmail.com>
License-File: LICENSE
Requires-Python: >=3.13
Requires-Dist: pip>=25.2
Requires-Dist: polars>=1.33.1
Requires-Dist: pyyaml>=6.0.2
Requires-Dist: xlsxwriter>=3.2.9
